fibberio/__init__.py
fibberio/cli.py
fibberio/distribution.py
fibberio/helpers.py
fibberio/range.py
fibberio/source.py
fibberio/task.py
fibberio-1.2.0.dist-info/entry_points.txt
fibberio-1.2.0.dist-info/LICENSE.md
fibberio-1.2.0.dist-info/WHEEL
fibberio-1.2.0.dist-info/METADATA
fibberio-1.2.0.dist-info/RECORD
