Metadata-Version: 2.1
Name: fibberio
Version: 1.2.0
Summary: 
Home-page: https://github.com/sethjuarez/fibberio
Author: sethjuarez
Author-email: me@sethjuarez.com
Requires-Python: >=3.9,<4.0
Classifier: Programming Language :: Python :: 3
Classifier: Programming Language :: Python :: 3.10
Classifier: Programming Language :: Python :: 3.9
Requires-Dist: PyYAML (>=6.0,<7.0)
Requires-Dist: click (>=8.0.3,<9.0.0)
Requires-Dist: numpy (>=1.22.2,<2.0.0)
Requires-Dist: pandas (>=1.4.1,<2.0.0)
Requires-Dist: parsimonious (>=0.8.1,<0.9.0)
